fds/__init__.py
fds/sdk/__init__.py
fds/sdk/FactSetFunds/__init__.py
fds/sdk/FactSetFunds/api_client.py
fds/sdk/FactSetFunds/configuration.py
fds/sdk/FactSetFunds/exceptions.py
fds/sdk/FactSetFunds/model_utils.py
fds/sdk/FactSetFunds/rest.py
fds/sdk/FactSetFunds/api/__init__.py
fds/sdk/FactSetFunds/api/distributions_api.py
fds/sdk/FactSetFunds/api/fund_flows__aum_api.py
fds/sdk/FactSetFunds/api/group_holdings_api.py
fds/sdk/FactSetFunds/api/helper_api.py
fds/sdk/FactSetFunds/api/market_aggregates_api.py
fds/sdk/FactSetFunds/api/prices__returns_api.py
fds/sdk/FactSetFunds/api/reference_api.py
fds/sdk/FactSetFunds/api/screening_operations_api.py
fds/sdk/FactSetFunds/apis/__init__.py
fds/sdk/FactSetFunds/model/__init__.py
fds/sdk/FactSetFunds/model/aum.py
fds/sdk/FactSetFunds/model/aum_request.py
fds/sdk/FactSetFunds/model/aum_response.py
fds/sdk/FactSetFunds/model/benchmark_details.py
fds/sdk/FactSetFunds/model/benchmark_details_request.py
fds/sdk/FactSetFunds/model/benchmark_details_response.py
fds/sdk/FactSetFunds/model/classifications.py
fds/sdk/FactSetFunds/model/classifications_request.py
fds/sdk/FactSetFunds/model/classifications_response.py
fds/sdk/FactSetFunds/model/content_set.py
fds/sdk/FactSetFunds/model/content_set_item.py
fds/sdk/FactSetFunds/model/content_sets_response.py
fds/sdk/FactSetFunds/model/costs_fees.py
fds/sdk/FactSetFunds/model/costs_fees_ids.py
fds/sdk/FactSetFunds/model/costs_fees_request.py
fds/sdk/FactSetFunds/model/costs_fees_response.py
fds/sdk/FactSetFunds/model/create_content_set_request.py
fds/sdk/FactSetFunds/model/create_content_set_request_body.py
fds/sdk/FactSetFunds/model/create_content_set_response.py
fds/sdk/FactSetFunds/model/create_content_set_response_data.py
fds/sdk/FactSetFunds/model/create_request_field_object.py
fds/sdk/FactSetFunds/model/criterion.py
fds/sdk/FactSetFunds/model/custom_content_set_item.py
fds/sdk/FactSetFunds/model/custom_content_sets.py
fds/sdk/FactSetFunds/model/data_type.py
fds_sdk_factsetfunds-2.2.0.dist-info/licenses/LICENSE
fds_sdk_factsetfunds-2.2.0.dist-info/METADATA
fds_sdk_factsetfunds-2.2.0.dist-info/WHEEL
fds_sdk_factsetfunds-2.2.0.dist-info/top_level.txt
fds_sdk_factsetfunds-2.2.0.dist-info/RECORD
